md2htmlpy/__init__.py
md2htmlpy/client.py
md2htmlpy/models.py
md2htmlpy-1.0.0.dist-info/LICENSE
md2htmlpy-1.0.0.dist-info/METADATA
md2htmlpy-1.0.0.dist-info/WHEEL
md2htmlpy-1.0.0.dist-info/top_level.txt
md2htmlpy-1.0.0.dist-info/RECORD
