Metadata-Version: 2.1
Name: md2htmlpy
Version: 1.0.0
Summary: Convert MD to HTML with full control over generated elements
Author-email: BlitzJB <blitz04.dev@gmail.com>
License: =?utf-8?q?The_MIT_License_=28MIT=29?=
Project-URL: Homepage, https://github.com/blitzjb/md2htmlpy
Keywords: markdown,html,markdowntohtml
Classifier: License :: OSI Approved :: MIT License
Classifier: Programming Language :: Python
Classifier: Programming Language :: Python :: 3
Requires-Python: >=3.8
License-File: LICENSE
